ipyllogger/__init__.py
ipyllogger/level.py
ipyllogger/logger.py
tests/__init__.py
tests/ipyllogger_test.py
ipyllogger-1.0.0.dist-info/LICENSE
ipyllogger-1.0.0.dist-info/METADATA
ipyllogger-1.0.0.dist-info/WHEEL
ipyllogger-1.0.0.dist-info/top_level.txt
ipyllogger-1.0.0.dist-info/RECORD
