Metadata-Version: 2.1
Name: ipyllogger
Version: 1.0.0
Summary: [SCHOOL PROJECT - PYTHON BASICS] | Minimum Python package to write logs in a file
Home-page: https://github.com/RagnarBob/Ilogger
Author: Makendy ALEXIS
Author-email: makendyalexis5414@gmail.com
Maintainer: Louis Midson LAJEANTY
Maintainer-email: mds@louismidson.me
Classifier: Programming Language :: Python :: 3
Classifier: License :: OSI Approved :: MIT License
Classifier: Operating System :: OS Independent
Requires-Python: >=3.8, <4
License-File: LICENSE
